{
  "id": "work-psof-pitch",
  "domain": "Work",
  "title": "PSOF Pitch Refinement for iConnections",
  "purpose": "Refine PSOF pitch—especially the elevator speech—for iConnections with Ethan and Eric",
  "status": "active",
  "created": "2026-01-20",
  "deadline": "End of February 2026",
  "actions": [
    "Review current pitch",
    "Draft and iterate elevator speech",
    "Incorporate feedback from Ethan and Eric",
    "Finalize concise version"
  ],
  "outcomes": [],
  "notes": "Time-sensitive. Needs to begin. iConnections at end of Feb (~5 weeks)."
}
